{"date": "2026-03-14", "alerts": {"CA": ["Event: Extreme Heat Watch\nArea: San Diego County Coastal Areas; ...","Event: Extreme Heat Watch\nArea: Santa Ana Mountains and Foothills\n...","Event: Extreme Heat Watch\nArea: Catalina and Santa Barbara Islands; ...","Event: Extreme Heat Watch\nArea: Santa Clarita Valley; ...","Event: Wind Advisory\nArea: Mojave Desert Slopes\n...","Event: Extreme Heat Watch\nArea: Parker Valley; ..."], "TX": ["Event: Fire Weather Watch\nArea: Llano; Burnet; ...","Event: Flood Warning\nArea: Angelina, TX; Nacogdoches, TX\n...","Event: Fire Weather Watch\nArea: South Central Lowlands And Southern Rio Grande Valley; ...","Event: High Wind Watch\nArea: Cimarron; Texas; ...","Event: Red Flag Warning\nArea: Cimarron; Texas; ...","Event: Fire Weather Watch\nArea: Cimarron; Texas; ...","Event: Fire Weather Watch\nArea: Ochiltree; Lipscomb; ...","Event: Fire Weather Watch\nArea: Parmer; Castro; ...","Event: High Wind Watch\nArea: Harper; Woods; ...","Event: High Wind Watch\nArea: Parmer; Castro; ...","Event: High Wind Watch\nArea: Guadalupe Mountains of Eddy County; ..."], "FL": ["Event: Dense Fog Advisory\nArea: Inland Collier County; ...","Event: Rip Current Statement\nArea: Coastal Nassau; ...","Event: Rip Current Statement\nArea: Coastal Palm Beach County\n...","Event: Rip Current Statement\nArea: Coastal Volusia; ...","Event: Rip Current Statement\nArea: Coastal Volusia; ..."]}}